{
  "openapi": "3.0.0",
  "info": {
    "title": "API - Inserção de dados de cosumo de API externo no Banco de dados",
    "description": "Essa API tem como Objeitvo gravar os dados de uma api externa para dentro do banco de dados e renderiazando no front-end",
    "contact": {
      "email": "carlosbandelliv@gmail.com"
    },
    "version": "1.0.0"
  },
  "servers": [
    {
      "url": "http://146.190.215.239:3333",
      "description": "API de test"
    }
  ],
  "paths": {
    "/movies": {
      "get": {
        "description": "Busca todos o filmes",
        "tags": ["Film"],
        "responses": {
          "200": {
            "description": "OK",
            "content": {
              "application/json": {
                "schema": {},
                "examples": {
                  "film": {
                    "value": {
                      "id": "ea660b10-85c4-4ae3-8a5f-41cea3648e3e",
                      "title": "Princess Mononoke",
                      "description": "Ashitaka, a prince of the disappearing Ainu tribe, is cursed by a demonized boar god and must journey to the west to find a cure. Along the way, he encounters San, a young human woman fighting to protect the forest, and Lady Eboshi, who is trying to destroy it. Ashitaka must find a way to bring balance to this conflict.",
                      "director": "Hayao Miyazaki",
                      "producer": "Toshio Suzuki",
                      "image": "https://image.tmdb.org/t/p/w600_and_h900_bestv2/jHWmNr7m544fJ8eItsfNk8fs2Ed.jpg"
                    }
                  }
                }
              }
            }
          }
        }
      }
    }
  }
}
